asyncTwitter/__init__.py
asyncTwitter/__version__.py
asyncTwitter/account.py
asyncTwitter/asyncAccount.py
asyncTwitter/asyncLogin.py
asyncTwitter/asyncScraper.py
asyncTwitter/asyncSearch.py
asyncTwitter/asyncUtil.py
asyncTwitter/constants.py
asyncTwitter/login.py
asyncTwitter/scraper.py
asyncTwitter/search.py
asyncTwitter/twoCaptcha.py
asyncTwitter/util.py
asyncTwitterClient-0.4.0.dist-info/LICENSE
asyncTwitterClient-0.4.0.dist-info/METADATA
asyncTwitterClient-0.4.0.dist-info/WHEEL
asyncTwitterClient-0.4.0.dist-info/top_level.txt
asyncTwitterClient-0.4.0.dist-info/RECORD
